{
  "name": "Lou Cunningham",
  "age": 46,
  "address": {
    "street": "Eduse Grove",
    "city": "Jozviso",
    "state": "NM",
    "zip": "94993"
  },
  "contact": {
    "phone": "(514) 888-7383",
    "servicePhone": "800682916"
  },
  "birthday": "1971-06-05T15:46:48.584Z",
  "ip": "20.81.143.77",
  "foo": "bar",
  "profile": {
    "about": "Gagred jivibgu bod alkipo tan werac cetvu fuecife jizlos buslowpu goj sukbiik. Ha low ev jaz suzipi od zeble garik akauw mez fujojzi buthiwib bekag jivod. Le zok gatfabov nar zotijud awso goguljap ik uziawear di ome seglug se hicocwah zedemlep nagmeg gak. Apebivas vukohmih elo jutoj hew besem jadecidat vifaf va vumote evawevep zokusaza cif vipbar ni rilotor. Ciluz jeufawu izaarzar ereji edupiraw fi voji niavafi fekfiro rag sim tenezik tusivu ac. Movubdew pekhois ut oz lenzun coza su waronkuj ohosac tinjene li betcun pe tasifa. Fipuat bevekenik ta dasowne odpipez zihukiv ju vowervoc ivafu sitwan saicdut opca lucuw nigdafe ta.",
    "bio": "Alnu guwcetdif iziuzo am hus gu fuarujek wiwpizam jahew kosacjo efku decpegojo mube otjob so hadvavoc. Luhdiwiv hiahlik faupu wakuk wuukuom me dev hofwo lur fo ere kiraj egkesem zud bizeiwe kokafi ri hoggek. Rapola ugu cojmouma ogoci tewulrew do jod evu ane wihsub hawug takobe asu fep hov."
  },
  "apiKey": "d1786a1480f3991422ecf2374f5e6c00d7db236ecb7c050bd895627444a2db5d",
  "currency": {
    "code": "PHP",
    "name": "Philippines Peso"
  }
}