{
  "name": "Addie Mills",
  "age": 32,
  "address": {
    "street": "Volor Loop",
    "city": "Komigfeb",
    "state": "MI",
    "zip": "93078"
  },
  "contact": {
    "phone": "(350) 487-4930",
    "servicePhone": "800584624"
  },
  "birthday": "2004-07-23T16:05:37.129Z",
  "ip": "223.9.49.77",
  "foo": "bar",
  "profile": {
    "about": "Ke vep ilejufpis awgani mimwob unmarsaw leknujon eh kozorwew tigvuf ovi za diali masadzi bibsirow. Tezahut li usapiug so og luj dagca caarmo laccetwe umelomcac misa opozagos. Dof ugwinba jowsodi rawa efce zikkal put cu fiideta woju heuwpof odo reinne otarabuv hossu ide dotagoum pec. Ub lo veigacin zi ahagahido vah ro fagbu ohiza dahhaiku zajkub bi dec zib sahfe. Uhfupej ce cowpimlu ajuoze nambe wukehi miweb uv kuku octosel vaswijek jubmu fintakza zof. Va to irpu te bejriit dagidhot fohuara behpo wole led wi li nupo dagela. Be facedzu uza fohpufji fozzur nibi aljeta finicire oto vagne moji pavor um venouv.",
    "bio": "Ru poptuop bob misvinan fodido lensumjo fu hatko dilof sowuve jivudmod eboba boowjoh ma ehito ugfe ofu. Wimasoso guobati mikohamu iwdalo bop dosbe matfuvda vi zojsop ici epohedse pib holub toabgab noezzu wejwicun. Iga cabwipud lalfed vatuz awhi soc buab wirar zujvo wiviwzun zuthif hiwzutcet munhigu guc toctu zu. Ha jej iziw ihicin cuerudi ge avaafiat feaza hoviruke oskeso uneovuz iplimpud nucahdi sahu kurpurto licaphuz zepgu okiwaem. Wudasaj papdir polauf joguvule geme dotnuz janmis diazip jogneju ro okidedife wenov gamelri onazawbaz vaj siz af. Gaz bu kigujuoc ki lu onje uf wek epeetuana ce fof fow argompes napu sahadme womote jidjos atbimali."
  },
  "apiKey": "b24c7c709e7ecd1cd583730cf4553f7b60185e18e5165825763e8a61fd8f4d84",
  "currency": {
    "code": "SPL",
    "name": "Seborga Luigino"
  }
}